gym_torcs/__init__.py
gym_torcs/sample_agent.py
gym_torcs/snakeoil3_gym.py
gym_torcs/torcs_env.py
gym_torcs-0.1.1.dist-info/METADATA
gym_torcs-0.1.1.dist-info/WHEEL
gym_torcs-0.1.1.dist-info/top_level.txt
gym_torcs-0.1.1.dist-info/RECORD
